[
  {
    "name": "Acadia",
    "state": "ME",
    "position": [
      44.216629,
      -68.345268
    ], "image": "public/images/acadia.png"
  },
  {
    "name": "Arches",
    "state": "UT",
    "position": [
      38.725055,
      -109.595467
    ], "image": "public/images/arches.png"
  },
  {
    "name": "Badlands",
    "state": "SD",
    "position": [
      43.699522,
      -102.393955
    ], "image": "public/images/badland.jpg"
  },
  {
    "name": "Big Bend",
    "state": "TX",
    "position": [
      29.333194,
      -103.310728
    ], "image": "public/images/bigbend.png"
  },
  {
    "name": "Biscayne",
    "state": "FL",
    "position": [
      25.481276,
      -80.218304
    ], "image": "public/images/biscayne.jpg"
  },
  {
    "name": "Black Canyon of the Gunnison",
    "state": "CO",
    "position": [
      38.57214,
      -107.723916
    ], "image": "public/images/blackcanyon.jpg"  
  },
  {
    "name": "Bryce Canyon",
    "state": "UT",
    "position": [
      37.57069,
      -112.178679
    ], "image": "public/images/bryce.png"
  },
  {
    "name": "Canyonlands",
    "state": "UT",
    "position": [
      38.233999,
      -109.949595
    ], "image": "public/images/badlands.png"
  },
  {
    "name": "Capitol Reef",
    "state": "UT",
    "position": [
      38.066514,
      -111.142734
    ], "image": "public/images/capitolreef.png"
  },
  {
    "name": "Carlsbad Caverns",
    "state": "NM",
    "position": [
      32.120039,
      -104.527775
    ], "image": "public/images/carlsbad.png"
  },
  {
    "name": "Channel Islands",
    "state": "CA",
    "position": [
      33.848661,
      -119.74032
    ], "image": "public/images/channelislands.png"
  },
  {
    "name": "Congaree",
    "state": "SC",
    "position": [
      33.794047,
      -80.735119
    ], "image": "public/images/congaree.png"
  },
  {
    "name": "Crater Lake",
    "state": "OR",
    "position": [
      42.709644,
      -122.424511
    ], "image": "public/images/craterlake.png"
  },
  {
    "name": "Cuyahoga Valley",
    "state": "OH",
    "position": [
      41.25511,
      -81.569692
    ], "image": "public/images/cuyahoga.png"
  },
  {
    "name": "Death Valley",
    "state": "CA",
    "position": [
      36.470232,
      -117.138803
    ], "image": "public/images/deathvalley.png"
  },
  {
    "name": "Denali",
    "state": "AK",
    "position": [
      63.231647,
      -150.602967
    ], "image": "public/images/denali.png"
  },
  {
    "name": "Dry Tortugas",
    "state": "FL",
    "position": [
      24.645728,
      -82.361704
    ], "image": "public/images/drytortugas.png"
  },
  {
    "name": "Everglades",
    "state": "FL",
    "position": [
      25.374575,
      -80.954659
    ], "image": "public/images/everglades.png"
  },
  {
    "name": "Gates of the Arctic",
    "state": "AK",
    "position": [
      67.837416,
      -153.386932
    ], "image": "public/images/gatesofthearctic.png"
  },
  {
    "name": "Gateway Arch",
    "state": "MO",
    "position": [
      38.62317,
      -90.180683
    ], "image": "public/images/gatewayarch.png"
  },
  {
    "name": "Glacier",
    "state": "MT",
    "position": [
      48.617398,
      -113.858424
    ], "image": "public/images/glacier.png"
  },
  {
    "name": "Glacier Bay",
    "state": "AK",
    "position": [
      58.821087,
      -136.865428
    ], "image": "public/images/glacierbay.png"
  },
  {
    "name": "Grand Canyon",
    "state": "AZ",
    "position": [
      36.307889,
      -112.783479
    ], "image": "public/images/grandcanyon.png"
  },
  {
    "name": "Grand Teton",
    "state": "WY",
    "position": [
      43.810971,
      -110.685587
    ], "image": "public/images/grandteton.png"
  },
  {
    "name": "Great Basin",
    "state": "NV",
    "position": [
      38.941593,
      -114.244268
    ], "image": "public/images/greatbasin.png"
  },
  {
    "name": "Great Sand Dunes",
    "state": "CO",
    "position": [
      37.79446,
      -105.613013
    ], "image": "public/images/greatsanddunes.png"
  },
  {
    "name": "Great Smoky Mountains",
    "state": "TN",
    "position": [
      35.635153,
      -83.505968
    ], "image": "public/images/greatsmokymountains.png"
  },
  {
    "name": "Guadalupe Mountains",
    "state": "TX",
    "position": [
      31.90681,
      -104.868278
    ], "image": "public/images/guadalupemountains.png"    
  },
  {
    "name": "Haleakala",
    "state": "HI",
    "position": [
      20.699418,
      -156.148603
    ], "image": "public/images/haleakala.png"
  },
  {
    "name": "Hawaii Volcanoes",
    "state": "HI",
    "position": [
      19.260804,
      -155.415649
    ], "image": "public/images/hawaiivolcanoes.png"
  },
  {
    "name": "Hot Springs",
    "state": "AR",
    "position": [
      34.529165,
      -93.065905
    ], "image": "public/images/hotsprings.png"
  },
  {
    "name": "Indiana Dunes",
    "state": "IN",
    "position": [
      41.612371,
      -87.149112
    ], "image": "public/images/indianadunes.png"
  },
  {
    "name": "Isle Royale",
    "state": "MI",
    "position": [
      47.712108,
      -88.794858
    ], "image": "public/images/isleroyale.png"
  },
  {
    "name": "Joshua Tree",
    "state": "CA",
    "position": [
      33.899774,
      -115.860134
    ], "image": "public/images/joshuatree.png"
  },
  {
    "name": "Katmai",
    "state": "AK",
    "position": [
      58.504775,
      -154.889462
    ], "image": "public/images/katmai.png"
  },
  {
    "name": "Kenai Fjords",
    "state": "AK",
    "position": [
      59.796514,
      -150.246592
    ], "image": "public/images/kenai.png"
  },
  {
    "name": "Kings Canyon",
    "state": "CA",
    "position": [
      36.915268,
      -118.65856
    ], "image": "public/images/kingscanyon.png"
  },
  {
    "name": "Kobuk Valley",
    "state": "AK",
    "position": [
      67.391355,
      -159.063112
    ], "image": "public/images/kobukvalley.png"
  },
  {
    "name": "Lake Clark",
    "state": "AK",
    "position": [
      60.682342,
      -153.261871
    ], "image": "public/images/lakeclark.png"
  },
  {
    "name": "Lassen Volcanic",
    "state": "CA",
    "position": [
      40.464766,
      -121.433435
    ], "image": "public/images/lassenvolcanic.png"
  },
  {
    "name": "Mammoth Cave",
    "state": "KY",
    "position": [
      37.188575,
      -86.140755
    ], "image": "public/images/mammothcave.png"
  },
  {
    "name": "Mesa Verde",
    "state": "CO",
    "position": [
      37.253474,
      -108.447174
    ], "image": "public/images/mesaverde.png"
  },
  {
    "name": "Mount Rainier",
    "state": "WA",
    "position": [
      46.906031,
      -121.786218
    ], "image": "public/images/mountrainier.png"
  },
  {
    "name": "National Park of American Samoa",
    "state": "SA",
    "position": [
      -14.225602,
      -170.072331
    ], "image": "public/images/american_samoa.png"
  },
  {
    "name": "New River Gorge",
    "state": "WV",
    "position": [
      37.8651,
      -81.0186
    ], "image": "public/images/newrivergorge.png"
  },
  {
    "name": "North Cascades",
    "state": "WA",
    "position": [
      48.685186,
      -121.136102
    ], "image": "public/images/northcascades.png"
  },
  {
    "name": "Olympic",
    "state": "WA",
    "position": [
      47.926301,
      -123.94598
    ], "image": "public/images/olympic.png"
  },
  {
    "name": "Petrified Forest",
    "state": "AZ",
    "position": [
      34.974643,
      -109.772657
    ], "image": "public/images/petrifiedforest.png"
  },
  {
    "name": "Pinnacles",
    "state": "CA",
    "position": [
      36.486284,
      -121.173379
    ], "image": "public/images/pinnacles.png"
  },
  {
    "name": "Redwood",
    "state": "CA",
    "position": [
      41.460686,
      -124.004459
    ], "image": "public/images/redwood.png" 
  },
  {
    "name": "Rocky Mountain",
    "state": "CO",
    "position": [
      40.355934,
      -105.703659
    ], "image": "public/images/rockymountain.png"
  },
  {
    "name": "Saguaro",
    "state": "AZ",
    "position": [
      32.228049,
      -110.871175
    ], "image": "public/images/saguaro.png"
  },
  {
    "name": "Sequoia",
    "state": "CA",
    "position": [
      36.496098,
      -118.577185
    ], "image": "public/images/sequoia.png"
  },
  {
    "name": "Shenandoah",
    "state": "VA",
    "position": [
      38.471926,
      -78.50474
    ], "image": "public/images/shenandoah.png"
  },
  {
    "name": "Theodore Roosevelt",
    "state": "ND",
    "position": [
      47.259952,
      -103.436874
    ], "image": "public/images/theodoreroosevelt.png"   
  },
  {
    "name": "Virgin Islands",
    "state": "VI",
    "position": [
      18.336902,
      -64.808812
    ], "image": "public/images/virginislands.png"
  },
  {
    "name": "Voyageurs",
    "state": "MN",
    "position": [
      48.465411,
      -92.828796
    ], "image": "public/images/voyageurs.png"
  },
  {
    "name": "White Sands",
    "state": "NM",
    "position": [
      32.764701,
      -106.309873
    ], "image": "public/images/whitesands.png"
  },
  {
    "name": "Wind Cave",
    "state": "SD",
    "position": [
      43.568849,
      -103.443732
    ], "image": "public/images/windcave.png"
  },
  {
    "name": "Wrangell - St Elias",
    "state": "AK",
    "position": [
      61.18059,
      -142.132011
    ], "image": "public/images/wrangell_st_elias.png"
  },
  {
    "name": "Yellowstone",
    "state": "WY",
    "position": [
      44.620714,
      -110.490063
    ], "image": "public/images/yellowstone.png"   
  },
  {
    "name": "Yosemite",
    "state": "CA",
    "position": [
      37.839349,
      -119.542841
    ], "image": "public/images/yosemite.png"
  },
  {
    "name": "Zion",
    "state": "UT",
    "position": [
      37.322823,
      -113.045728
    ], "image": "public/images/zion.png"
  }
]
